pyslab/__init__.py
pyslab/board.py
pyslab/generator.py
pyslab/solver.py
pyslab/validator.py
pyslab-0.1.0.dist-info/LICENSE
pyslab-0.1.0.dist-info/METADATA
pyslab-0.1.0.dist-info/WHEEL
pyslab-0.1.0.dist-info/top_level.txt
pyslab-0.1.0.dist-info/RECORD
